{
	"name": "swiggy_large",
	"properties": {
		"activities": [
			{
				"name": "Git_to_DataLake",
				"type": "Copy",
				"state": "Inactive",
				"onInactiveMarkAs": "Succeeded",
				"dependsOn": [],
				"policy": {
					"timeout": "0.12:00:00",
					"retry": 0,
					"retryIntervalInSeconds": 30,
					"secureOutput": false,
					"secureInput": false
				},
				"userProperties": [],
				"typeProperties": {
					"source": {
						"type": "JsonSource",
						"storeSettings": {
							"type": "HttpReadSettings",
							"requestMethod": "GET"
						},
						"formatSettings": {
							"type": "JsonReadSettings"
						}
					},
					"sink": {
						"type": "JsonSink",
						"storeSettings": {
							"type": "AzureBlobFSWriteSettings"
						},
						"formatSettings": {
							"type": "JsonWriteSettings"
						}
					},
					"enableStaging": false
				},
				"inputs": [
					{
						"referenceName": "sourcedataset",
						"type": "DatasetReference"
					}
				],
				"outputs": [
					{
						"referenceName": "sinkdataset",
						"type": "DatasetReference"
					}
				]
			},
			{
				"name": "Notebook1",
				"type": "DatabricksNotebook",
				"dependsOn": [
					{
						"activity": "Git_to_DataLake",
						"dependencyConditions": [
							"Succeeded"
						]
					}
				],
				"policy": {
					"timeout": "0.12:00:00",
					"retry": 0,
					"retryIntervalInSeconds": 30,
					"secureOutput": false,
					"secureInput": false
				},
				"userProperties": [],
				"typeProperties": {
					"notebookPath": "/Users/kk_insights@outlook.com/Case study/error_simulation"
				},
				"linkedServiceName": {
					"referenceName": "AzureDatabricks1",
					"type": "LinkedServiceReference"
				}
			},
			{
				"name": "Archive",
				"type": "Copy",
				"dependsOn": [
					{
						"activity": "Notebook3",
						"dependencyConditions": [
							"Succeeded"
						]
					}
				],
				"policy": {
					"timeout": "0.12:00:00",
					"retry": 0,
					"retryIntervalInSeconds": 30,
					"secureOutput": false,
					"secureInput": false
				},
				"userProperties": [],
				"typeProperties": {
					"source": {
						"type": "JsonSource",
						"storeSettings": {
							"type": "AzureBlobFSReadSettings",
							"recursive": true,
							"enablePartitionDiscovery": false
						},
						"formatSettings": {
							"type": "JsonReadSettings"
						}
					},
					"sink": {
						"type": "ParquetSink",
						"storeSettings": {
							"type": "AzureBlobFSWriteSettings"
						},
						"formatSettings": {
							"type": "ParquetWriteSettings"
						}
					},
					"enableStaging": false
				},
				"inputs": [
					{
						"referenceName": "main_archive_source",
						"type": "DatasetReference"
					}
				],
				"outputs": [
					{
						"referenceName": "archive_sink",
						"type": "DatasetReference"
					}
				]
			},
			{
				"name": "Notebook2",
				"type": "DatabricksNotebook",
				"dependsOn": [
					{
						"activity": "Notebook1",
						"dependencyConditions": [
							"Succeeded"
						]
					}
				],
				"policy": {
					"timeout": "0.12:00:00",
					"retry": 0,
					"retryIntervalInSeconds": 30,
					"secureOutput": false,
					"secureInput": false
				},
				"userProperties": [],
				"typeProperties": {
					"notebookPath": "/Users/kk_insights@outlook.com/success_simulation"
				},
				"linkedServiceName": {
					"referenceName": "AzureDatabricks1",
					"type": "LinkedServiceReference"
				}
			},
			{
				"name": "Append Notebook2 Log",
				"type": "AppendVariable",
				"dependsOn": [
					{
						"activity": "Notebook2",
						"dependencyConditions": [
							"Completed"
						]
					}
				],
				"userProperties": [],
				"typeProperties": {
					"variableName": "append_var",
					"value": {
						"value": "@concat('{\"startTime\":\"',utcNow(),'\",\"endTime\":\"',utcNow(),'\",\"processId\":\"',activity('Notebook2').ActivityRunId,'\",\"processName\":\"Notebook2\",\"status\":\"',activity('Notebook2').Status,'\",\"errorMessage\":\"', activity('Notebook2').output?.runError,'\"}')\n",
						"type": "Expression"
					}
				}
			},
			{
				"name": "Append Notebook1 Log",
				"type": "AppendVariable",
				"dependsOn": [
					{
						"activity": "Notebook1",
						"dependencyConditions": [
							"Completed"
						]
					}
				],
				"userProperties": [],
				"typeProperties": {
					"variableName": "append_var",
					"value": {
						"value": "@concat('{\"startTime\":\"',utcNow(),'\",\"endTime\":\"',utcNow(),'\",\"processId\":\"',activity('Notebook1').ActivityRunId,'\",\"processName\":\"Notebook1\",\"status\":\"',activity('Notebook1').Status,'\",\"errorMessage\":\"', activity('Notebook1').output?.runError,'\"}')\n",
						"type": "Expression"
					}
				}
			},
			{
				"name": "Append Archive Log",
				"type": "AppendVariable",
				"dependsOn": [
					{
						"activity": "Archive",
						"dependencyConditions": [
							"Completed"
						]
					}
				],
				"userProperties": [],
				"typeProperties": {
					"variableName": "append_var",
					"value": {
						"value": "@concat('{\"startTime\":\"',utcNow(),'\",\"endTime\":\"',utcNow(),'\",\"processId\":\"', activity('Archive').ActivityRunId,'\",\"processName\":\"Archive\",\"status\":\"',activity('Archive').Status,'\",\"errorMessage\":\"',activity('Archive').Error?.message,'\"}')\n",
						"type": "Expression"
					}
				}
			},
			{
				"name": "ForEach1",
				"type": "ForEach",
				"dependsOn": [
					{
						"activity": "Append Notebook2 Log",
						"dependencyConditions": [
							"Completed",
							"Skipped"
						]
					},
					{
						"activity": "Append Notebook1 Log",
						"dependencyConditions": [
							"Completed",
							"Skipped"
						]
					},
					{
						"activity": "Append Archive Log",
						"dependencyConditions": [
							"Completed",
							"Skipped"
						]
					},
					{
						"activity": "Append Copy Data Log",
						"dependencyConditions": [
							"Completed",
							"Skipped"
						]
					},
					{
						"activity": "Append Delete Log",
						"dependencyConditions": [
							"Completed",
							"Skipped"
						]
					},
					{
						"activity": "Append Notebook3 Log",
						"dependencyConditions": [
							"Completed",
							"Skipped"
						]
					}
				],
				"userProperties": [],
				"typeProperties": {
					"items": {
						"value": "@variables('append_var')",
						"type": "Expression"
					},
					"isSequential": true,
					"activities": [
						{
							"name": "Set variable3",
							"type": "SetVariable",
							"dependsOn": [],
							"policy": {
								"secureOutput": false,
								"secureInput": false
							},
							"userProperties": [],
							"typeProperties": {
								"variableName": "log",
								"value": {
									"value": "@item()",
									"type": "Expression"
								}
							}
						},
						{
							"name": "Stored procedure_copy1",
							"type": "SqlServerStoredProcedure",
							"dependsOn": [
								{
									"activity": "Set variable3",
									"dependencyConditions": [
										"Succeeded"
									]
								}
							],
							"policy": {
								"timeout": "0.12:00:00",
								"retry": 0,
								"retryIntervalInSeconds": 30,
								"secureOutput": false,
								"secureInput": false
							},
							"userProperties": [],
							"typeProperties": {
								"storedProcedureName": "[dbo].[usp_LogPipelineExecution]",
								"storedProcedureParameters": {
									"End_Time": {
										"value": {
											"value": "@json(variables('log')).endTime",
											"type": "Expression"
										},
										"type": "Datetime"
									},
									"Message": {
										"value": {
											"value": "@json(variables('log')).errorMessage",
											"type": "Expression"
										},
										"type": "String"
									},
									"Process_Id": {
										"value": {
											"value": "@json(variables('log')).processId",
											"type": "Expression"
										},
										"type": "String"
									},
									"Process_Name": {
										"value": {
											"value": "@json(variables('log')).processName",
											"type": "Expression"
										},
										"type": "String"
									},
									"Start_Time": {
										"value": {
											"value": "@json(variables('log')).startTime",
											"type": "Expression"
										},
										"type": "Datetime"
									},
									"Status": {
										"value": {
											"value": "@json(variables('log')).status",
											"type": "Expression"
										},
										"type": "String"
									}
								}
							},
							"linkedServiceName": {
								"referenceName": "sqlconnector",
								"type": "LinkedServiceReference"
							}
						}
					]
				}
			},
			{
				"name": "Append Copy Data Log",
				"type": "AppendVariable",
				"dependsOn": [
					{
						"activity": "Git_to_DataLake",
						"dependencyConditions": [
							"Completed"
						]
					}
				],
				"userProperties": [],
				"typeProperties": {
					"variableName": "append_var",
					"value": {
						"value": "@concat('{\"startTime\":\"',utcNow(),'\",\"endTime\":\"',utcNow(),'\",\"processId\":\"', activity('Git_to_DataLake').ActivityRunId,'\",\"processName\":\"Copy Data\",\"status\":\"',activity('Git_to_DataLake').Status,'\",\"errorMessage\":\"',activity('Git_to_DataLake').Error?.message,'\"}')\n",
						"type": "Expression"
					}
				}
			},
			{
				"name": "Get Metadata1",
				"type": "GetMetadata",
				"dependsOn": [
					{
						"activity": "Archive",
						"dependencyConditions": [
							"Succeeded"
						]
					}
				],
				"policy": {
					"timeout": "0.12:00:00",
					"retry": 0,
					"retryIntervalInSeconds": 30,
					"secureOutput": false,
					"secureInput": false
				},
				"userProperties": [],
				"typeProperties": {
					"dataset": {
						"referenceName": "main_archive_source",
						"type": "DatasetReference"
					},
					"fieldList": [
						"exists"
					],
					"storeSettings": {
						"type": "AzureBlobFSReadSettings",
						"recursive": true,
						"enablePartitionDiscovery": false
					},
					"formatSettings": {
						"type": "JsonReadSettings"
					}
				}
			},
			{
				"name": "If Condition1",
				"type": "IfCondition",
				"dependsOn": [
					{
						"activity": "Archive",
						"dependencyConditions": [
							"Succeeded"
						]
					},
					{
						"activity": "Get Metadata1",
						"dependencyConditions": [
							"Succeeded"
						]
					}
				],
				"userProperties": [],
				"typeProperties": {
					"expression": {
						"value": "@activity('Get Metadata1').output.exists",
						"type": "Expression"
					},
					"ifFalseActivities": [
						{
							"name": "Fail1",
							"type": "Fail",
							"dependsOn": [],
							"userProperties": [],
							"typeProperties": {
								"message": "FileNotFound",
								"errorCode": "2200"
							}
						}
					],
					"ifTrueActivities": [
						{
							"name": "Delete1",
							"type": "Delete",
							"state": "Inactive",
							"onInactiveMarkAs": "Succeeded",
							"dependsOn": [],
							"policy": {
								"timeout": "0.12:00:00",
								"retry": 0,
								"retryIntervalInSeconds": 30,
								"secureOutput": false,
								"secureInput": false
							},
							"userProperties": [],
							"typeProperties": {
								"dataset": {
									"referenceName": "archieve_source",
									"type": "DatasetReference"
								},
								"logStorageSettings": {
									"linkedServiceName": {
										"referenceName": "AzureDataLakeStorage1",
										"type": "LinkedServiceReference"
									},
									"path": "swiggydataset/Delete_Log"
								},
								"enableLogging": true,
								"storeSettings": {
									"type": "AzureBlobFSReadSettings",
									"recursive": true,
									"enablePartitionDiscovery": false
								}
							}
						}
					]
				}
			},
			{
				"name": "Append Delete Log",
				"type": "AppendVariable",
				"dependsOn": [
					{
						"activity": "If Condition1",
						"dependencyConditions": [
							"Completed"
						]
					}
				],
				"userProperties": [],
				"typeProperties": {
					"variableName": "append_var",
					"value": {
						"value": "@concat(\n    '{\"startTime\":\"', utcNow(), '\",',\n    '\"endTime\":\"', utcNow(), '\",',\n    '\"processId\":\"', \n        if(\n            activity('Get Metadata1').output.exists,\n            activity('Delete1').ActivityRunId, \n            activity('Fail1').ActivityRunId\n        ),\n    '\",\"processName\":\"Delete1\",',\n    '\"status\":\"', \n        if(\n            activity('Get Metadata1').output.exists,\n            activity('Delete1').Status, \n            'Failed'\n        ),\n    '\",',\n    '\"errorMessage\":\"',\n        if(\n            activity('Get Metadata1').output.exists,\n            activity('Delete1').Error?.message, \n            activity('Fail1').output.message\n        ),\n    '\"}'\n)",
						"type": "Expression"
					}
				}
			},
			{
				"name": "Notebook3",
				"type": "DatabricksNotebook",
				"dependsOn": [
					{
						"activity": "Notebook2",
						"dependencyConditions": [
							"Succeeded"
						]
					}
				],
				"policy": {
					"timeout": "0.12:00:00",
					"retry": 0,
					"retryIntervalInSeconds": 30,
					"secureOutput": false,
					"secureInput": false
				},
				"userProperties": [],
				"typeProperties": {
					"notebookPath": "/Users/kk_insights@outlook.com/success_simulation"
				},
				"linkedServiceName": {
					"referenceName": "AzureDatabricks1",
					"type": "LinkedServiceReference"
				}
			},
			{
				"name": "Append Notebook3 Log",
				"type": "AppendVariable",
				"dependsOn": [
					{
						"activity": "Notebook3",
						"dependencyConditions": [
							"Completed"
						]
					}
				],
				"userProperties": [],
				"typeProperties": {
					"variableName": "append_var",
					"value": {
						"value": "@concat('{\"startTime\":\"',utcNow(),'\",\"endTime\":\"',utcNow(),'\",\"processId\":\"',activity('Notebook3').ActivityRunId,'\",\"processName\":\"Notebook3\",\"status\":\"',activity('Notebook3').Status,'\",\"errorMessage\":\"', activity('Notebook3').output?.runError,'\"}')\n",
						"type": "Expression"
					}
				}
			}
		],
		"variables": {
			"append_var": {
				"type": "Array"
			},
			"log": {
				"type": "String"
			}
		},
		"annotations": [],
		"lastPublishTime": "2024-12-11T10:13:45Z"
	},
	"type": "Microsoft.DataFactory/factories/pipelines"
}